model_render
