Metadata-Version: 1.0
Name: django-model-render
Version: 0.3
Summary: Django models extension that allows define default model templates
Home-page: https://github.com/a1fred/django-model-render
Author: a1fred
Author-email: demalf@gmail.com
License: MIT
Platform: any
